./.env.example
./.gitignore
./LICENSE
./PKG-INFO
./README.md
./__init__.py
./__main__.py
./luhuo_qwen3_mt_mcp_server.py
./pyproject.toml
luhuo_qwen3_mt_mcp_server-1.0.11.dist-info/METADATA
luhuo_qwen3_mt_mcp_server-1.0.11.dist-info/WHEEL
luhuo_qwen3_mt_mcp_server-1.0.11.dist-info/entry_points.txt
luhuo_qwen3_mt_mcp_server-1.0.11.dist-info/licenses/LICENSE
luhuo_qwen3_mt_mcp_server-1.0.11.dist-info/RECORD
