Metadata-Version: 2.4
Name: luhuo-qwen3-mt-mcp-server
Version: 1.0.11
Summary: 基于阿里云通义千问翻译模型的MCP服务器，支持92种语言互译、流式翻译、术语干预和领域提示
Author-email: 炉火 <chenrongjie@luhuokj.com>
License-File: LICENSE
Requires-Python: >=3.10
Requires-Dist: build>=1.3.0
Requires-Dist: mcp[cli]>=1.9.4
Requires-Dist: openai>=1.86.0
Requires-Dist: requests>=2.31.0
Requires-Dist: twine>=6.1.0
Requires-Dist: typing-extensions>=4.0.0
